pygifconvt_daun/__init__.py
pygifconvt_daun/converter.py
pygifconvt_daun-1.0.3.dist-info/LICENSE
pygifconvt_daun-1.0.3.dist-info/METADATA
pygifconvt_daun-1.0.3.dist-info/WHEEL
pygifconvt_daun-1.0.3.dist-info/top_level.txt
pygifconvt_daun-1.0.3.dist-info/RECORD
