Metadata-Version: 2.1
Name: pygifconvt-daun
Version: 1.0.3
Summary: Test package for distribution
Home-page: 
Download-URL: 
Author: daunj 
Author-email: otl267@naver.com
Keywords: GIFCONVERTER,gifconverter
Classifier: Programming Language :: Python :: 3
Classifier: License :: OSI Approved :: MIT License
Classifier: Operating System :: OS Independent
Requires-Python: >=3
License-File: LICENSE
Requires-Dist: pillow
